quollio_data_profiler/__init__.py
quollio_data_profiler/snowflake_lineage_profiler.py
quollio_data_profiler/snowflake_stats_profiler.py
quollio_data_profiler/core/__init__.py
quollio_data_profiler/core/core.py
quollio_data_profiler/core/setup.py
quollio_data_profiler/profilers/lineage_profiler.py
quollio_data_profiler/profilers/stats_profiler.py
quollio_data_profiler/profilers/dbt_projects/snowflake_lineage_profiler/README.md
quollio_data_profiler/profilers/dbt_projects/snowflake_lineage_profiler/dbt_project.yml
quollio_data_profiler/profilers/dbt_projects/snowflake_lineage_profiler/package-lock.yml
quollio_data_profiler/profilers/dbt_projects/snowflake_lineage_profiler/packages.yml
quollio_data_profiler/profilers/dbt_projects/snowflake_lineage_profiler/analyses/.gitkeep
quollio_data_profiler/profilers/dbt_projects/snowflake_lineage_profiler/macros/.gitkeep
quollio_data_profiler/profilers/dbt_projects/snowflake_lineage_profiler/models/profilers/column_to_column_lineage.sql
quollio_data_profiler/profilers/dbt_projects/snowflake_lineage_profiler/models/profilers/schema.yml
quollio_data_profiler/profilers/dbt_projects/snowflake_lineage_profiler/models/profilers/table_to_table_lineage.sql
quollio_data_profiler/profilers/dbt_projects/snowflake_lineage_profiler/seeds/.gitkeep
quollio_data_profiler/profilers/dbt_projects/snowflake_lineage_profiler/snapshots/.gitkeep
quollio_data_profiler/profilers/dbt_projects/snowflake_stats_profiler/README.md
quollio_data_profiler/profilers/dbt_projects/snowflake_stats_profiler/dbt_project.yml
quollio_data_profiler/profilers/dbt_projects/snowflake_stats_profiler/package-lock.yml
quollio_data_profiler/profilers/dbt_projects/snowflake_stats_profiler/packages.yml
quollio_data_profiler/profilers/dbt_projects/snowflake_stats_profiler/analyses/.gitkeep
quollio_data_profiler/profilers/dbt_projects/snowflake_stats_profiler/macros/.gitkeep
quollio_data_profiler-0.2.1.dist-info/LICENSE
quollio_data_profiler-0.2.1.dist-info/WHEEL
quollio_data_profiler-0.2.1.dist-info/METADATA
quollio_data_profiler-0.2.1.dist-info/RECORD
