Metadata-Version: 2.1
Name: quollio-data-profiler
Version: 0.2.1
Summary: Quollio Data Profiler
Requires-Python: >=3.8
Classifier: Programming Language :: Python
Classifier: Programming Language :: Python :: 3
Classifier: Programming Language :: Python :: 3.8
Classifier: Programming Language :: Python :: 3.9
Classifier: Programming Language :: Python :: 3.10
Classifier: Programming Language :: Python :: 3.11
Classifier: License :: OSI Approved :: MIT License
Classifier: Operating System :: OS Independent
Classifier: Development Status :: 3 - Alpha
Classifier: Intended Audience :: Developers
Classifier: Topic :: Software Development :: Libraries :: Python Modules
Requires-Dist: blake3==0.3.3
Requires-Dist: dbt-core==1.7.2
Requires-Dist: dbt-snowflake==1.7.0
Requires-Dist: jinja2==3.1.2
Requires-Dist: PyYAML==6.0.1
Requires-Dist: requests==2.31.0
Requires-Dist: snowflake-connector-python==3.5.0
Project-URL: Source, https://github.com/QuollioLabs/quollio-data-profiler
